README.txt
setup.py
scripts/senti_classifier
src/senti_classifier/__init__.py
src/senti_classifier/bag_of_words.py
src/senti_classifier/senti_classifier.py
src/sentiment_classifier.egg-info/PKG-INFO
src/sentiment_classifier.egg-info/SOURCES.txt
src/sentiment_classifier.egg-info/dependency_links.txt
src/sentiment_classifier.egg-info/top_level.txt