Metadata-Version: 1.0
Name: sentiment-classifier
Version: 0.4
Summary: Sentiment Classification using Word Sense Disambiguation, Senti Word Net and word occurance statistics using movie review corpus
Home-page: http://www.jaist.ac.jp/~s1010205/home
Author: KATHURIA Pulkit
Author-email: pulkit@jaist.ac.jp
License: LICENSE.txt
Keywords: http://www.jaist.ac.jp/~s1010205/pybits/pybits.html.LyXconv/pybits.html#x1-40003
Platform: UNKNOWN
Classifier: Development Status :: 4 - Beta
Classifier: Natural Language :: English
Classifier: Topic :: Scientific/Engineering :: Artificial Intelligence
